cvee/__init__.py
cvee/types.py
cvee/common/__init__.py
cvee/common/config.py
cvee/common/history_buffer.py
cvee/common/registry.py
cvee/common/seed.py
cvee/io/__init__.py
cvee/io/io.py
cvee/io/handlers/__init__.py
cvee/io/handlers/base.py
cvee/io/handlers/bin_handler.py
cvee/io/handlers/geometry_handler.py
cvee/io/handlers/image_handler.py
cvee/io/handlers/json_handler.py
cvee/io/handlers/npy_handler.py
cvee/io/handlers/npz_handler.py
cvee/io/handlers/pickle_handler.py
cvee/io/handlers/txt_handler.py
cvee/io/handlers/xml_handler.py
cvee/io/handlers/yaml_handler.py
cvee/nn/__init__.py
cvee/nn/mlp.py
cvee/nn/pointnet.py
cvee/nn/pointnet2.py
cvee/nn/vae.py
cvee/reps/__init__.py
cvee/reps/box2d.py
cvee/reps/box3d.py
cvee/transforms/__init__.py
cvee/transforms/rotation.py
cvee/transforms/transforms.py
cvee/transforms/utils.py
cvee/utils/__init__.py
cvee/utils/console.py
cvee/utils/log.py
cvee/utils/misc.py
cvee/utils/progress.py
cvee/utils/rand.py
cvee/utils/timer.py
cvee/utils/types.py
cvee/vis/__init__.py
cvee/vis/color.py
cvee/vis/image.py
cvee/vis/o3d.py
cvee-0.0.6.dist-info/LICENSE
cvee-0.0.6.dist-info/METADATA
cvee-0.0.6.dist-info/WHEEL
cvee-0.0.6.dist-info/entry_points.txt
cvee-0.0.6.dist-info/top_level.txt
cvee-0.0.6.dist-info/RECORD
