Metadata-Version: 2.1
Name: cvee
Version: 0.0.6
Summary: A set of tools for CV researchers
Home-page: https://github.com/jianglongye/cvee
Author: Jianglong Ye
Author-email: jianglong.yeh@gmail.com
Project-URL: Bug Tracker, https://github.com/jianglongye/cvee/issues
Classifier: Programming Language :: Python :: 3
Classifier: License :: OSI Approved :: MIT License
Classifier: Operating System :: OS Independent
Requires-Python: >=3.6
License-File: LICENSE
Requires-Dist: numpy
Requires-Dist: opencv-python
Requires-Dist: pyyaml
Requires-Dist: yacs
Requires-Dist: rich
Requires-Dist: matplotlib
